Metadata-Version: 2.1
Name: collection-framework
Version: 1.0
License-File: LICENSE
